[{"uf":"AL","data":"30\/11\/2021","gasolina":6.72,"gasolinapostos":202,"gasolinaa":6.8,"gasolinaapostos":157,"diesel":5.69,"dieselpostos":99,"etanol":5.33,"etanolpostos":192,"diesels10":5.68,"diesels10postos":180,"gnv":4.68,"gnvpostos":23},{"uf":"AM","data":"29\/11\/2021","gasolina":6.74,"gasolinapostos":281,"gasolinaa":6.69,"gasolinaapostos":193,"diesel":5.48,"dieselpostos":153,"etanol":5.34,"etanolpostos":188,"diesels10":5.53,"diesels10postos":205,"gnv":4.14,"gnvpostos":4},{"uf":"BA","data":"30\/11\/2021","gasolina":6.79,"gasolinapostos":1035,"gasolinaa":6.89,"gasolinaapostos":914,"diesel":5.49,"dieselpostos":488,"etanol":5.6,"etanolpostos":1038,"diesels10":5.56,"diesels10postos":900,"gnv":3.99,"gnvpostos":100},{"uf":"CE","data":"30\/11\/2021","gasolina":6.96,"gasolinapostos":853,"gasolinaa":7.09,"gasolinaapostos":712,"diesel":5.76,"dieselpostos":143,"etanol":5.71,"etanolpostos":800,"diesels10":5.74,"diesels10postos":785,"gnv":4.74,"gnvpostos":66},{"uf":"ES","data":"30\/11\/2021","gasolina":6.77,"gasolinapostos":394,"gasolinaa":6.89,"gasolinaapostos":354,"diesel":5.12,"dieselpostos":148,"etanol":5.9,"etanolpostos":313,"diesels10":5.23,"diesels10postos":341,"gnv":4.5,"gnvpostos":80},{"uf":"GO","data":"30\/11\/2021","gasolina":7.19,"gasolinapostos":725,"gasolinaa":7.3,"gasolinaapostos":417,"diesel":5.52,"dieselpostos":384,"etanol":5.33,"etanolpostos":716,"diesels10":5.69,"diesels10postos":599},{"uf":"MA","data":"30\/11\/2021","gasolina":6.51,"gasolinapostos":290,"gasolinaa":6.65,"gasolinaapostos":223,"diesel":5.41,"dieselpostos":92,"etanol":5.64,"etanolpostos":201,"diesels10":5.42,"diesels10postos":275},{"uf":"MG","data":"30\/11\/2021","gasolina":7.09,"gasolinapostos":1962,"gasolinaa":7.21,"gasolinaapostos":1190,"diesel":5.4,"dieselpostos":1095,"etanol":5.55,"etanolpostos":1950,"diesels10":5.47,"diesels10postos":1436,"gnv":4.38,"gnvpostos":32},{"uf":"PA","data":"30\/11\/2021","gasolina":6.85,"gasolinapostos":404,"gasolinaa":6.98,"gasolinaapostos":265,"diesel":5.7,"dieselpostos":225,"etanol":6.17,"etanolpostos":126,"diesels10":5.72,"diesels10postos":353},{"uf":"PB","data":"30\/11\/2021","gasolina":6.53,"gasolinapostos":266,"gasolinaa":6.66,"gasolinaapostos":157,"diesel":5.37,"dieselpostos":97,"etanol":5.08,"etanolpostos":249,"diesels10":5.52,"diesels10postos":243,"gnv":4.69,"gnvpostos":47},{"uf":"PE","data":"30\/11\/2021","gasolina":6.68,"gasolinapostos":768,"gasolinaa":6.82,"gasolinaapostos":485,"diesel":5.36,"dieselpostos":72,"etanol":5.28,"etanolpostos":716,"diesels10":5.4,"diesels10postos":714,"gnv":3.95,"gnvpostos":101},{"uf":"PR","data":"30\/11\/2021","gasolina":6.55,"gasolinapostos":1344,"gasolinaa":6.7,"gasolinaapostos":1099,"diesel":5.14,"dieselpostos":625,"etanol":5.49,"etanolpostos":1353,"diesels10":5.22,"diesels10postos":1106,"gnv":4.44,"gnvpostos":25},{"uf":"RJ","data":"30\/11\/2021","gasolina":7.3,"gasolinapostos":1457,"gasolinaa":7.42,"gasolinaapostos":1244,"diesel":5.28,"dieselpostos":554,"etanol":6.36,"etanolpostos":1432,"diesels10":5.36,"diesels10postos":1190,"gnv":4.47,"gnvpostos":548},{"uf":"RS","data":"30\/11\/2021","gasolina":7.09,"gasolinapostos":1408,"gasolinaa":7.21,"gasolinaapostos":1404,"diesel":5.28,"dieselpostos":958,"etanol":6.98,"etanolpostos":451,"diesels10":5.35,"diesels10postos":1184,"gnv":4.83,"gnvpostos":87},{"uf":"SC","data":"30\/11\/2021","gasolina":6.58,"gasolinapostos":882,"gasolinaa":6.67,"gasolinaapostos":812,"diesel":5.25,"dieselpostos":343,"etanol":6.12,"etanolpostos":572,"diesels10":5.3,"diesels10postos":742,"gnv":4.39,"gnvpostos":159},{"uf":"SE","data":"30\/11\/2021","gasolina":6.73,"gasolinapostos":179,"gasolinaa":6.85,"gasolinaapostos":150,"diesel":5.55,"dieselpostos":78,"etanol":5.46,"etanolpostos":140,"diesels10":5.67,"diesels10postos":173,"gnv":4.47,"gnvpostos":42},{"uf":"SP","data":"30\/11\/2021","gasolina":6.41,"gasolinapostos":6832,"gasolinaa":6.6,"gasolinaapostos":4808,"diesel":5.29,"dieselpostos":2713,"etanol":5.22,"etanolpostos":6873,"diesels10":5.39,"diesels10postos":5264,"gnv":3.95,"gnvpostos":235},{"uf":"AP","data":"24\/11\/2021","gasolina":5.93,"gasolinapostos":96,"gasolinaa":6.32,"gasolinaapostos":8,"diesel":5.4,"dieselpostos":28,"etanol":5.9,"etanolpostos":1,"diesels10":5.57,"diesels10postos":20},{"uf":"MT","data":"30\/11\/2021","gasolina":6.76,"gasolinapostos":711,"gasolinaa":6.87,"gasolinaapostos":355,"diesel":5.76,"dieselpostos":379,"etanol":5.35,"etanolpostos":707,"diesels10":5.82,"diesels10postos":623,"gnv":3.11,"gnvpostos":15},{"uf":"PI","data":"30\/11\/2021","gasolina":7.14,"gasolinapostos":233,"gasolinaa":7.35,"gasolinaapostos":203,"diesel":5.58,"dieselpostos":105,"etanol":5.73,"etanolpostos":191,"diesels10":5.63,"diesels10postos":210},{"uf":"RN","data":"30\/11\/2021","gasolina":7.13,"gasolinapostos":207,"gasolinaa":7.2,"gasolinaapostos":215,"diesel":5.66,"dieselpostos":150,"etanol":5.71,"etanolpostos":218,"diesels10":5.89,"diesels10postos":198,"gnv":4.84,"gnvpostos":33},{"uf":"AC","data":"30\/11\/2021","gasolina":7.12,"gasolinapostos":166,"gasolinaa":7.12,"gasolinaapostos":128,"diesel":6.23,"dieselpostos":151,"etanol":6.15,"etanolpostos":83,"diesels10":6.24,"diesels10postos":162},{"uf":"RO","data":"30\/11\/2021","gasolina":6.77,"gasolinapostos":162,"gasolinaa":6.87,"gasolinaapostos":133,"diesel":5.63,"dieselpostos":121,"etanol":6.19,"etanolpostos":82,"diesels10":5.67,"diesels10postos":141},{"uf":"RR","data":"30\/11\/2021","gasolina":6.38,"gasolinapostos":56,"gasolinaa":6.51,"gasolinaapostos":46,"diesel":5.62,"dieselpostos":43,"etanol":6.03,"etanolpostos":14,"diesels10":5.67,"diesels10postos":54},{"uf":"TO","data":"29\/11\/2021","gasolina":6.97,"gasolinapostos":133,"gasolinaa":7.06,"gasolinaapostos":79,"diesel":5.46,"dieselpostos":90,"etanol":5.71,"etanolpostos":106,"diesels10":5.48,"diesels10postos":127},{"uf":"DF","data":"24\/11\/2021","gasolina":7.1,"gasolinapostos":188,"gasolinaa":7.22,"gasolinaapostos":154,"diesel":5.54,"dieselpostos":95,"etanol":6.15,"etanolpostos":188,"diesels10":5.68,"diesels10postos":138},{"uf":"MS","data":"30\/11\/2021","gasolina":6.59,"gasolinapostos":287,"gasolinaa":6.72,"gasolinaapostos":192,"diesel":5.27,"dieselpostos":203,"etanol":5.46,"etanolpostos":288,"diesels10":5.37,"diesels10postos":233,"gnv":4.51,"gnvpostos":9}]
